alphatwirl/__init__.py
alphatwirl/_version.py
alphatwirl/binning/Binning.py
alphatwirl/binning/Combine.py
alphatwirl/binning/Echo.py
alphatwirl/binning/ReturnTrue.py
alphatwirl/binning/Round.py
alphatwirl/binning/RoundLog.py
alphatwirl/binning/__init__.py
alphatwirl/binning/search.py
alphatwirl/collector/ToDataFrame.py
alphatwirl/collector/ToDataFrameWithDatasetColumn.py
alphatwirl/collector/ToTupleList.py
alphatwirl/collector/ToTupleListWithDatasetColumn.py
alphatwirl/collector/WriteListToFile.py
alphatwirl/collector/WritePandasDataFrameToFile.py
alphatwirl/collector/__init__.py
alphatwirl/concurrently/CommunicationChannel.py
alphatwirl/concurrently/CommunicationChannel0.py
alphatwirl/concurrently/MultiprocessingDropbox.py
alphatwirl/concurrently/SubprocessRunner.py
alphatwirl/concurrently/TaskPackageDropbox.py
alphatwirl/concurrently/WorkingArea.py
alphatwirl/concurrently/__init__.py
alphatwirl/concurrently/example_load.py
alphatwirl/concurrently/example_load_result.py
alphatwirl/concurrently/exec_util.py
alphatwirl/concurrently/run.py
alphatwirl/concurrently/testing.py
alphatwirl/concurrently/condor/__init__.py
alphatwirl/concurrently/condor/commands.py
alphatwirl/concurrently/condor/exec_util.py
alphatwirl/concurrently/condor/submitter.py
alphatwirl/configure/TableConfigCompleter.py
alphatwirl/configure/TableFileNameComposer.py
alphatwirl/configure/__init__.py
alphatwirl/configure/build_counter_collector_pair.py
alphatwirl/datasetloop/__init__.py
alphatwirl/datasetloop/collector.py
alphatwirl/datasetloop/loop.py
alphatwirl/datasetloop/reader.py
alphatwirl/datasetloop/resume.py
alphatwirl/loop/Collector.py
alphatwirl/loop/CollectorDelegate.py
alphatwirl/loop/DatasetIntoEventBuildersSplitter.py
alphatwirl/loop/EventLoop.py
alphatwirl/loop/EventLoopRunner.py
alphatwirl/loop/MPEventLoopRunner.py
alphatwirl/loop/NullCollector.py
alphatwirl/loop/ReaderComposite.py
alphatwirl/loop/__init__.py
alphatwirl/loop/deprecated.py
alphatwirl/loop/merge.py
alphatwirl-0.30.0.dist-info/LICENSE
alphatwirl-0.30.0.dist-info/METADATA
alphatwirl-0.30.0.dist-info/WHEEL
alphatwirl-0.30.0.dist-info/top_level.txt
alphatwirl-0.30.0.dist-info/RECORD
