Metadata-Version: 2.1
Name: alphatwirl
Version: 0.30.0
Summary: A Python library for summarizing event data
Home-page: https://github.com/alphatwirl/alphatwirl
Author: Tai Sakuma
Author-email: tai.sakuma@gmail.com
License: UNKNOWN
Platform: UNKNOWN
Classifier: Development Status :: 4 - Beta
Classifier: Intended Audience :: Science/Research
Classifier: License :: OSI Approved :: BSD License
Classifier: Programming Language :: Python :: 3.6
Classifier: Programming Language :: Python :: 3.7
Classifier: Programming Language :: Python :: 3.8
Requires-Dist: numpy
Requires-Dist: atpbar (>=1.0.8)
Requires-Dist: mantichora (>=0.10.0)
